{
  "_doc": "Rolling wire-services bigram corpus. Anchor for tilt_index.py. Bigrams keyed as 'a|b' (pipe-joined adjacent stopword-filtered tokens). Counts ≥ 2 only — singletons are noise.",
  "window_days": 90,
  "n_days_with_wire": 2,
  "n_articles": 9,
  "n_distinct_bigrams": 764,
  "n_bigrams_kept": 98,
  "n_total_bigram_tokens": 888,
  "bigrams": {
    "bateau|croisière": 5,
    "with|iran": 4,
    "croisière|hondiu": 4,
    "china|based": 3,
    "based|refinery": 3,
    "president|donald": 3,
    "donald|trump": 3,
    "busines|with": 3,
    "exchange|fire": 3,
    "troi|mort": 3,
    "navire|croisière": 3,
    "passager|hondiu": 3,
    "sont|mort": 3,
    "direct|hantaviru": 3,
    "dont|troi": 3,
    "organisation|mondiale": 3,
    "mondiale|santé": 3,
    "risque|pour": 3,
    "absolument|faible": 3,
    "troi|passager": 3,
    "continue|trade": 3,
    "trade|blow": 3,
    "impos|sanction": 2,
    "sanction|china": 2,
    "refinery|shipper": 2,
    "shipper|iranian": 2,
    "secondary|sanction": 2,
    "sanction|compan": 2,
    "strait|hormuz": 2,
    "buyer|iranian": 2,
    "financial|institution": 2,
    "know|exchange": 2,
    "fire|iran": 2,
    "hantaviru|troi": 2,
    "troi|suspect": 2,
    "suspect|débarqué": 2,
    "débarqué|vert": 2,
    "vert|françai": 2,
    "françai|identifié": 2,
    "identifié|comme": 2,
    "comme|contact": 2,
    "foyer|hantaviru": 2,
    "dans|atlantique": 2,
    "hantaviru|sait": 2,
    "sait|navire": 2,
    "croisière|confiné": 2,
    "confiné|large": 2,
    "large|vert": 2,
    "souche|ande": 2,
    "troi|personn": 2,
    "pioneering|founder": 2,
    "founder|turner": 2,
    "turner|dies": 2,
    "turner|outspoken": 2,
    "outspoken|founder": 2,
    "founder|dies": 2,
    "dies|reuter": 2,
    "hantaviru|réunion": 2,
    "réunion|internationale": 2,
    "internationale|cour": 2,
    "cour|pour": 2,
    "pour|gérer": 2,
    "gérer|rapatriement": 2,
    "rapatriement|passager": 2,
    "considéré|comme": 2,
    "comme|suspect": 2,
    "dans|archipel": 2,
    "être|rapatrié": 2,
    "vers|leur": 2,
    "leur|pays": 2,
    "pays|origine": 2,
    "christian|lindmeier": 2,
    "porte|parole": 2,
    "devant|presse": 2,
    "hantaviru|bateau": 2,
    "croisière|risque": 2,
    "pour|ensemble": 2,
    "ensemble|population": 2,
    "population|absolument": 2,
    "faible|assure": 2,
    "agit|viru": 2,
    "viru|dangereux": 2,
    "dangereux|mais": 2,
    "mais|uniquement": 2,
    "uniquement|pour": 2,
    "pour|personne": 2,
    "personne|réellement": 2,
    "réellement|infectée": 2,
    "hondiu|dont": 2,
    "passager|sont": 2,
    "pour|population": 2,
    "ressortissant|britannique": 2,
    "moin|contagieux": 2,
    "contagieux|covid": 2,
    "israel|hezbollah": 2,
    "hezbollah|continue": 2,
    "blow|ceasefire": 2,
    "ceasefire|israel": 2
  },
  "meta_version": "7.3.0"
}
